{
  "$schema": "https://mintlify.com/docs.json",
  "theme": "mint",
  "name": "Unpod Dev",
  "icons": {
    "library": "lucide"
  },
  "colors": {
    "primary": "#796cff",
    "light": "#9a90ff",
    "dark": "#5a4fff"
  },
  "favicon": "/favicon.svg",
  "logo": {
    "light": "/logo/dark.svg",
    "dark": "/logo/light.svg",
    "href": "https://unpod.dev"
  },
  "navigation": {
    "tabs": [
      {
        "tab": "Get Started",
        "groups": [
          {
            "group": "Get Started",
            "icon": "book",
            "pages": [
              "introduction",
              "platform",
              "quickstart",
              "configuration",
              "architecture"
            ]
          }
        ]
      },
      {
        "tab": "Voice AI",
        "groups": [
          {
            "group": "Getting Started",
            "icon": "book-open",
            "pages": [
              "Voice AI/introduction"
            ]
          },
          {
            "group": "Space View",
            "icon": "grid-2x2",
            "pages": [
              "Voice AI/Space View/introduction",
              "Voice AI/Space View/conversation",
              "Voice AI/Space View/calls",
              "Voice AI/Space View/people",
              "Voice AI/Space View/analytics"
            ]
          },
          {
            "group": "Studio View",
            "icon": "layout-panel-left",
            "pages": [
              "Voice AI/Studio View/dashboard",
              {
                "group": "Agents",
                "pages": [
                  "Voice AI/Studio View/identity",
                  "Voice AI/Studio View/persona",
                  "Voice AI/Studio View/voice profile",
                  "Voice AI/Studio View/telephony",
                  "Voice AI/Studio View/advance",
                  "Voice AI/Studio View/analysis",
                  "Voice AI/Studio View/integration"
                ]
              },
              "Voice AI/Studio View/knowledge base",
              "Voice AI/Studio View/call logs",
              "Voice AI/Studio View/api key"
            ]
          }
        ]
      },
      {
        "tab": "Dev Platform",
        "groups": [
           {
            "group": "Getting Started",
            "icon": "book-open",
            "pages": [
              "Dev Platform/introduction"
            ]
          },
          {
            "group": "Dev Platform",
            "icon": "sliders-horizontal",
            "pages": [
              "Dev Platform/telephony",
              "Dev Platform/numbers",
              "Dev Platform/provider",
              "Dev Platform/agents",
              "Dev Platform/Analytics-and-Reporting",
              "Dev Platform/Load-Testing",
              "Dev Platform/Security-&-Compliance"
            ]
          }
        ]
      },
      {
        "tab": "API Documentation",
        "groups": [
          {
            "group": "Get Started",
            "icon": "book-open",
            "pages": [
              "api/get-started/quickstart",
              "api/get-started/authentication"
            ]
          },
          {
            "group": "Space",
            "icon": "layout-grid",
            "pages": [
              "api/space/organizations",
              "api/space/spaces"

            ]
          },
          {
            "group": "Execution",
            "icon": "activity",
            "pages": [
              "api/execution/tasks",
              "api/execution/runs"
            ]
          },
          {
            "group": "Logs",
            "icon": "file-text",
            "pages": [
              "api/logs/calls"
            ]
          },
          {
            "group": "Provider",
            "icon": "server",
            "pages": [
              "api/telephony/Providers",
              "api/provider/configurations"
            ]
          },
          {
            "group": "Telephony",
            "icon": "phone",
            "pages": [
              "api/telephony/numbers",
              "api/telephony/bridges"
            ]
          },
          {
            "group": "Billing & Usage",
            "icon": "credit-card",
            "pages": [
              "api/billing&usage/analytics",
              "api/billing&usage/billing"
            ]
          }
        ]
      }
    ],
    "global": {
      "anchors": [
        {
          "anchor": "YouTube",
          "href": "https://www.youtube.com/@unpod-ai",
          "icon": "youtube"
        },
        {
          "anchor": "GitHub",
          "href": "https://github.com/parvbhullar",
          "icon": "github"
        },
        {
          "anchor": "Discord",
          "href": "https://discord.gg/7kQ4ewNSHZ",
          "icon": "discord"
        }
      ]
    }
  },
  "navbar": {
    "links": [
      {
        "label": "Documentation",
        "href": "https://docs.unpod.dev/"
      }
    ],
    "primary": {
      "type": "button",
      "label": "Dashboard",
      "href": "https://unpod.dev"
    }
  },
  "footer": {
    "socials": {
      "github": "https://github.com/parvbhullar",
      "twitter": "https://x.com/unpod_ai",
      "youtube": "https://www.youtube.com/@unpod-ai",
      "discord": "https://discord.gg/7kQ4ewNSHZ"
    }
  },
  "redirects": [
    {
      "source": "/",
      "destination": "/introduction"
    }
  ]
}
